{
  "$schema": "https://mintlify.com/docs.json",
  "name": "Defaults",
  "theme": "palm",
  "colors": {
    "primary": "#fb502d",
    "light": "#fb9252",
    "dark": "#fc7c7c"
  },
  "favicon": "https://media.brand.dev/e0c92337-76d6-4ce9-b894-817f449d688e.svg",
  "navbar": {
    "primary": {
      "type": "github",
      "href": "https://github.com/sindresorhus/Defaults"
    }
  },
  "footer": {
    "socials": {
      "github": "https://github.com/sindresorhus/Defaults"
    }
  },
  "navigation": {
    "tabs": [
      {
        "tab": "Documentation",
        "groups": [
          {
            "group": "Get Started",
            "pages": [
              "introduction",
              "installation",
              "quickstart"
            ]
          },
          {
            "group": "Guides",
            "pages": [
              "guides/defining-keys",
              "guides/swiftui",
              "guides/observation",
              "guides/icloud-sync",
              "guides/custom-types",
              "guides/migrations"
            ]
          },
          {
            "group": "Advanced",
            "pages": [
              "advanced/observable-macro",
              "advanced/combine",
              "advanced/suites",
              "advanced/any-serializable"
            ]
          }
        ]
      },
      {
        "tab": "API Reference",
        "groups": [
          {
            "group": "Core",
            "pages": [
              "api/defaults",
              "api/key",
              "api/serializable"
            ]
          },
          {
            "group": "Bridges",
            "pages": [
              "api/bridges-overview",
              "api/built-in-bridges"
            ]
          },
          {
            "group": "SwiftUI & Observation",
            "pages": [
              "api/default-property-wrapper",
              "api/defaults-toggle",
              "api/updates",
              "api/publisher"
            ]
          },
          {
            "group": "iCloud",
            "pages": [
              "api/icloud"
            ]
          }
        ]
      }
    ]
  }
}
